schwab_sdk/LICENSE
schwab_sdk/README.md
schwab_sdk/__init__.py
schwab_sdk/accounts.py
schwab_sdk/async_accounts.py
schwab_sdk/async_client.py
schwab_sdk/async_orders.py
schwab_sdk/async_streaming.py
schwab_sdk/authentication.py
schwab_sdk/callback.py
schwab_sdk/client.py
schwab_sdk/market.py
schwab_sdk/orders.py
schwab_sdk/streaming.py
schwab_sdk/token_handler.py
schwab_sdk_unofficial-0.2.7.dist-info/licenses/LICENSE
schwab_sdk_unofficial-0.2.7.dist-info/METADATA
schwab_sdk_unofficial-0.2.7.dist-info/WHEEL
schwab_sdk_unofficial-0.2.7.dist-info/top_level.txt
schwab_sdk_unofficial-0.2.7.dist-info/RECORD
