Metadata-Version: 2.4
Name: schwab_sdk_unofficial
Version: 0.2.7
Summary: Cliente ligero para API de Schwab: OAuth, REST y Streaming WebSocket
Author: Schwab SDK Contributors
License-Expression: MIT
Project-URL: Homepage, https://pypi.org/project/schwab-sdk/
Project-URL: Repository, https://github.com/your-org/schwab-sdk
Keywords: schwab,trading,market-data,websocket,sdk,api
Classifier: Programming Language :: Python :: 3
Classifier: Operating System :: OS Independent
Requires-Python: >=3.9
License-File: LICENSE
Requires-Dist: requests>=2.31.0
Requires-Dist: websocket-client>=1.8.0
Requires-Dist: Flask>=3.1.0
Requires-Dist: cryptography>=41.0.0
Requires-Dist: aiohttp>=3.8.0
Requires-Dist: websockets>=11.0.0
Dynamic: license-file
